sequential/ADD_SUB/add_1bit.v
module add_1bit(a,b,c_in,sum,c_out);

input a,b,c_in;
output sum,c_out;

//implementing a 1-bit full adder

// gate implementation for the sum
xor X1(w1, a, b);
xor X2(sum, w1, c_in);

// gate implementation for the carry bit
and A1(w2, a, b);
and A2(w3, w1, c_in);
or O1(c_out, w2, w3);

endmodule

pipe/ADD_SUB/add_1bit_test.v
module test_add_1bit();

reg a,b,c_in;
wire signed sum;
wire c_out;
integer i;

add_1bit Adder(a,b,c_in,sum,c_out);

initial 
    begin
        $dumpfile("add_1bit_test.vcd");
        $dumpvars(0, test_add_1bit);
        {a,b,c_in} = 0;

        $monitor($time, ": a=%b, b=%b, c_in=%b, sum=%b, cout=%b\n", a,b,c_in, sum, c_out);
            for(i = 0; i < 8; i = i + 1) begin
                #5 {a,b,c_in} = i;
            end
    end
endmodule

pipe/ADD_SUB/add_1bit_test.vcd
$date
	Mon Jan 31 18:00:37 2022
$end
$version
	Icarus Verilog
$end
$timescale
	1s
$end
$scope module test_add_1bit $end
$var wire 1 ! sum $end
$var wire 1 " c_out $end
$var reg 1 # a $end
$var reg 1 $ b $end
$var reg 1 % c_in $end
$var integer 32 & i [31:0] $end
$scope module Adder $end
$var wire 1 # a $end
$var wire 1 $ b $end
$var wire 1 % c_in $end
$var wire 1 " c_out $end
$var wire 1 ! sum $end
$var wire 1 ' w1 $end
$var wire 1 ( w2 $end
$var wire 1 ) w3 $end
$upscope $end
$upscope $end
$enddefinitions $end
#0
$dumpvars
0)
0(
0'
b0 &
0%
0$
0#
0"
0!
$end
#5
b1 &
#10
1!
b10 &
1%
#15
1'
1!
b11 &
1$
0%
#20
1"
0!
1)
b100 &
1%
#25
0"
1!
0)
b101 &
1#
0$
0%
#30
1"
0!
1)
b110 &
1%
#35
0'
1(
0!
0)
b111 &
1$
0%
#40
1!
b1000 &
1%
